camus/__init__.py
camus/config.py
camus/forms.py
camus/message_handler.py
camus/models.py
camus/routes.py
camus/util.py
camus/static/css/app.css
camus/static/css/icons.css
camus/static/dist/index.js
camus/static/dist/index.js.LICENSE.txt
camus/static/fonts/MaterialIcons-Regular.ttf
camus/static/fonts/MaterialIcons-Regular.woff
camus/static/fonts/MaterialIcons-Regular.woff2
camus/static/js/index.tsx
camus/static/js/mediaUtils.ts
camus/static/js/store.ts
camus/static/js/types.ts
camus/templates/base.html
camus/templates/bootstrap-base.html
camus/templates/chat.html
camus/templates/chatroom.html
camus/templates/join-room.html
camus/templates/public.html
camus/templates/react-base.html
camus_chat-0.3.1.data/scripts/camus
camus_chat-0.3.1.dist-info/LICENSE
camus_chat-0.3.1.dist-info/METADATA
camus_chat-0.3.1.dist-info/WHEEL
camus_chat-0.3.1.dist-info/top_level.txt
camus_chat-0.3.1.dist-info/RECORD
