Metadata-Version: 2.1
Name: camus-chat
Version: 0.3.1
Summary: Peer-to-peer video chat using WebRTC
Home-page: https://camus.chat/
Author: Morgan Robertson
Author-email: mrgnr@pm.me
License: AGPL-3.0-or-later
Download-URL: https://pypi.org/project/camus-chat/
Project-URL: Code, https://github.com/mrgnr/camus
Project-URL: Issue tracker, https://github.com/mrgnr/camus/issues
Project-URL: Documentation, https://docs.camus.chat/
Platform: UNKNOWN
Classifier: License :: OSI Approved :: GNU Affero General Public License v3 or later (AGPLv3+)
Classifier: Environment :: Web Environment
Classifier: Programming Language :: Python :: 3.7
Classifier: Programming Language :: Python :: 3.8
Classifier: Topic :: Communications :: Conferencing
Classifier: Topic :: Multimedia :: Video
Requires-Python: >=3.7
Requires-Dist: alembic (==1.5.2)
Requires-Dist: bootstrap-flask (==1.3.1)
Requires-Dist: flask-sqlalchemy (==2.4.4)
Requires-Dist: flask-wtf (==0.14.3)
Requires-Dist: hypercorn (==0.11.1)
Requires-Dist: python-slugify (==4.0.1)
Requires-Dist: quart (==0.14.1)
Requires-Dist: SQLAlchemy (==1.3.23)
Requires-Dist: twilio (==6.45.4)
Requires-Dist: werkzeug (==1.0.1)
